{
  "projects": [
    "project1",
    "project2",
    "project3",
    "project4444444 444444"
  ],
  "dashboards": [
    {
      "developer": "a",
      "project": "project4444444 444444",
      "id": 2
    },
    {
      "developer": "a",
      "project": "project3",
      "id": 3
    },
    {
      "developer": "a",
      "project": "project2",
      "id": 4
    },
    {
      "developer": "a",
      "project": "project3",
      "id": 5
    },
    {
      "developer": "a",
      "project": "project2",
      "id": 6
    },
    {
      "developer": "a",
      "project": "project3",
      "id": 7
    },
    {
      "developer": "a",
      "project": "project2",
      "id": 8
    },
    {
      "developer": "a",
      "project": "project3",
      "id": 9
    },
    {
      "developer": "a",
      "project": "project2",
      "id": 10
    },
    {
      "developer": "a",
      "project": "project3",
      "id": 11
    },
    {
      "developer": "a",
      "project": "project2",
      "id": 12
    },
    {
      "developer": "a",
      "project": "project3",
      "id": 13
    }
  ],
  "requirements": [
    {
      "project": "project4444444 444444",
      "resource": "name55555 555555555555",
      "hours": "8",
      "id": 2
    },
    {
      "project": "project3",
      "resource": "name3",
      "hours": "5",
      "id": 3
    },
    {
      "project": "project2",
      "resource": "name2",
      "hours": "8",
      "id": 4
    },
    {
      "project": "project3",
      "resource": "name4",
      "hours": "5",
      "id": 5
    },
    {
      "project": "project2",
      "resource": "name55555 555555555555",
      "hours": "8",
      "id": 6
    },
    {
      "project": "project3",
      "resource": "name2",
      "hours": "5",
      "id": 7
    },
    {
      "project": "project2",
      "resource": "name55555 555555555555",
      "hours": "8",
      "id": 8
    },
    {
      "project": "project3",
      "resource": "name55555 555555555555",
      "hours": "5",
      "id": 9
    },
    {
      "project": "project2",
      "resource": "name4",
      "hours": "8",
      "id": 10
    },
    {
      "project": "project3",
      "resource": "name4",
      "hours": "5",
      "id": 11
    },
    {
      "project": "project2",
      "resource": "name4",
      "hours": "8",
      "id": 12
    },
    {
      "project": "project3",
      "resource": "name4",
      "hours": "5",
      "id": 13
    }
  ],
  "project_manager": [
    {
      "id": "cnlcd",
      "name": "name1",
      "projects": [
        {
          "project": "Project2",
          "assignee": "name1"
        }
      ]
    },
    {
      "id": "cmcmx",
      "name": "name2",
      "projects": [
        {
          "project": "Project3",
          "assignee": "name12"
        },
        {
          "project": "Project4",
          "assignee": "name13"
        }
      ]
    },
    {
      "id": "okowc",
      "name": "name3",
      "projects": [
        {
          "project": "Project5",
          "assignee": "name14"
        },
        {
          "project": "Project6",
          "assignee": "name15"
        }
      ]
    },
    {
      "name": "a",
      "id": "1K-gIPM",
      "projects": []
    },
    {
      "name": "abc",
      "id": "ZQTD3jS",
      "projects": []
    },
    {
      "name": "a",
      "id": "YPVxSjo",
      "projects": []
    },
    {
      "name": "aaa",
      "id": "1UCMeTj",
      "projects": []
    },
    {
      "name": "abc",
      "projects": "",
      "id": "JHdojUf"
    },
    {
      "name": "aaaa",
      "projects": "",
      "id": "3iVtk5w"
    }
  ],
  "projectlist": [
    {
      "id": "1",
      "project": "project1",
      "resources": "3"
    },
    {
      "id": "2",
      "project": "project2",
      "resources": "2"
    },
    {
      "id": "3",
      "project": "project3",
      "resources": "5"
    },
    {
      "id": "4",
      "project": "project1",
      "resources": "3"
    },
    {
      "id": "5",
      "project": "project2",
      "resources": "2"
    },
    {
      "id": "6",
      "project": "project3",
      "resources": "5"
    },
    {
      "id": "7",
      "project": "project1",
      "resources": "3"
    },
    {
      "id": "8",
      "project": "project2",
      "resources": "2"
    },
    {
      "id": "9",
      "project": "project3",
      "resources": "5"
    },
    {
      "id": "10",
      "project": "project1",
      "resources": "3"
    },
    {
      "id": "11",
      "project": "project2",
      "resources": "2"
    },
    {
      "id": "12",
      "project": "project3",
      "resources": "5"
    },
    {
      "id": "13",
      "project": "project1",
      "resources": "3"
    },
    {
      "id": "14",
      "project": "project2",
      "resources": "2"
    },
    {
      "id": "15",
      "project": "project3",
      "resources": "5"
    }
  ],
  "availability": [
    {
      "available": [
        {
          "name": "name1"
        },
        {
          "name": "name2"
        },
        {
          "name": "name3"
        },
        {
          "name": "name1"
        },
        {
          "name": "name2"
        },
        {
          "name": "name3"
        },
        {
          "name": "name1"
        },
        {
          "name": "name2"
        },
        {
          "name": "name3"
        },
        {
          "name": "name1"
        },
        {
          "name": "name2"
        },
        {
          "name": "name3"
        },
        {
          "name": "name1"
        },
        {
          "name": "name2"
        },
        {
          "name": "name3"
        }
      ],
      "onLeave": [
        {
          "name": "name4"
        }
      ],
      "notYetIn": [
        {
          "name": "name7"
        },
        {
          "name": "name8"
        }
      ]
    }
  ],
  "resources": [
    "name1",
    "name2",
    "name3",
    "name4",
    "name55555 555555555555"
  ]
}